primeGraph/__init__.py
primeGraph/constants.py
primeGraph/types.py
primeGraph/buffer/__init__.py
primeGraph/buffer/base.py
primeGraph/buffer/factory.py
primeGraph/buffer/history.py
primeGraph/buffer/incremental.py
primeGraph/buffer/last_value.py
primeGraph/checkpoint/__init__.py
primeGraph/checkpoint/base.py
primeGraph/checkpoint/local_storage.py
primeGraph/checkpoint/postgresql.py
primeGraph/checkpoint/serialization.py
primeGraph/graph/__init__.py
primeGraph/graph/base.py
primeGraph/graph/engine.py
primeGraph/graph/executable.py
primeGraph/graph/llm_clients.py
primeGraph/graph/llm_tools.py
primeGraph/graph/tool_validation.py
primeGraph/models/__init__.py
primeGraph/models/checkpoint.py
primeGraph/models/state.py
primeGraph/utils/class_utils.py
primeGraph/web/__init__.py
primeGraph/web/graph_wrapper.py
primeGraph/web/models.py
primeGraph/web/service.py
primegraph-1.9.10.dist-info/METADATA
primegraph-1.9.10.dist-info/WHEEL
primegraph-1.9.10.dist-info/entry_points.txt
primegraph-1.9.10.dist-info/licenses/LICENSE
primegraph-1.9.10.dist-info/RECORD
