Metadata-Version: 2.4
Name: primeGraph
Version: 1.9.10
Summary: A lightweight graph approach to LLM workflows.
Project-URL: repository, https://github.com/fmeiraf/primeGraph
Author-email: Fernando Meira <fmeira.filho@gmail.com>
License: MIT
License-File: LICENSE
Requires-Python: <4.0,>=3.11
Requires-Dist: graphviz<1.0.0,>=0.20.3
Requires-Dist: psycopg2-binary<3.0.0,>=2.9.10
Requires-Dist: pydantic<3.0.0,>=2.9.2
Requires-Dist: redis>=5.2.1
Requires-Dist: rich<14.0.0,>=13.9.4
